{
    "portal": {
        "setToken": {
            "url": "token/(?P<param>(.*))",
            "func": "setToken"
        }
    },
    "diagnosis": {},
    "models": {
        "flsisppal": {
            "auth_group": null,
            "auth_user": null
        },
        "fldiagppal": {
            "yb_regdiagnosis": null,
            "yb_subregdiagnosis": null,
            "yb_log": null,
            "yb_procesos": null
        },
        "flfactppal": {
            "clientes": null
        }
    }
}
